heapqueue/__init__.py
heapq_container-0.1.dist-info/LICENSE
heapq_container-0.1.dist-info/METADATA
heapq_container-0.1.dist-info/WHEEL
heapq_container-0.1.dist-info/top_level.txt
heapq_container-0.1.dist-info/RECORD
