Metadata-Version: 2.1
Name: heapq-container
Version: 0.1
Summary: a Container datatype wrapper for the Python standard library heapq module
Author: lonnen
License: Apache-2.0
Project-URL: Homepage, https://github.com/lonnen/heapq-container
Project-URL: Changelog, https://github.com/lonnen/heapq-container/releases
Project-URL: Issues, https://github.com/lonnen/heapq-container/issues
Project-URL: CI, https://github.com/lonnen/heapq-container/actions
Classifier: License :: OSI Approved :: Apache Software License
Requires-Python: >=3.8
License-File: LICENSE
Provides-Extra: test
Requires-Dist: pytest ; extra == 'test'
